{
    "Metadata": {
        "Input bits": 256,
        "Program started at": "2025-09-16 16:20:13.801446+09:00",
        "Elapsed time": 0,
        "Entropy": 160.0,
        "Strength": "Very Strong"
    },
    "Message": "9:zbv~3cK1w;ltnju.'Xy#J$eyJFu4a*",
    "Generated hash": "10b678568f5479b38427adc0c9b33611f3bb6a6705fdf7c7f106aab3dd8d8071",
    "Correct   hash": "10b678568f5479b38427adc0c9b33611f3bb6a6705fdf7c7f106aab3dd8d8071",
    "Rounds logs": {
        "Preprocess": {
            "Block 0": [
                "0x393a7a62",
                "0x767e3363",
                "0x4b31773b",
                "0x6c746e6a",
                "0x752e2758",
                "0x79234a24",
                "0x65794a46",
                "0x7534612a",
                "0x80000000",
                "0x00000000",
                "0x00000000",
                "0x00000000",
                "0x00000000",
                "0x00000000",
                "0x00000000",
                "0x00000100"
            ]
        },
        "1st round": {
            "Message Schedule(Step1)": [
                "0x393a7a62",
                "0x767e3363",
                "0x4b31773b",
                "0x6c746e6a",
                "0x752e2758",
                "0x79234a24",
                "0x65794a46",
                "0x7534612a",
                "0x80000000",
                "0x00000000",
                "0x00000000",
                "0x00000000",
                "0x00000000",
                "0x00000000",
                "0x00000000",
                "0x00000100",
                "0x7e3661f7",
                "0x995cd228",
                "0x0ad9528c",
                "0x9784fd09",
                "0x8da28b53",
                "0x2d17a4b3",
                "0xbc60a4b7",
                "0x2b2f99e1",
                "0x603f03bd",
                "0x4a9fcda0",
                "0xf93610e1",
                "0xad191742",
                "0xf76a32ec",
                "0x65c2ea21",
                "0x8a85d9d7",
                "0x01d47310",
                "0x975ccab1",
                "0x986af317",
                "0xf2bb8bff",
                "0xcb3a4c8d",
                "0x32f62ff6",
                "0x795c4bba",
                "0xb18a6139",
                "0x25694fa8",
                "0x2ff057c8",
                "0x24707659",
                "0xbab10701",
                "0x61b6a1c5",
                "0x091046d5",
                "0x64400ec7",
                "0x189eb22b",
                "0x7bd05e97",
                "0xcc1c7798",
                "0x7af19b63",
                "0x9b50f61a",
                "0x34d4a6be",
                "0x6656b973",
                "0x569d1c45",
                "0xbff6fc4f",
                "0x9f994fc4",
                "0xf7b47020",
                "0xa3e1d321",
                "0xd4341705",
                "0x566ee343",
                "0x6af61988",
                "0xcbbb925e",
                "0xbe4ffd2d",
                "0x64d8a620"
            ],
            "Initialize working variables(Step2)": {
                "a": "0x6a09e667",
                "b": "0xbb67ae85",
                "c": "0x3c6ef372",
                "d": "0xa54ff53a",
                "e": "0x510e527f",
                "f": "0x9b05688c",
                "g": "0x1f83d9ab",
                "h": "0x5be0cd19"
            },
            "Main Compute Function loops(Step3)": {
                "1st loop": {
                    "a": "0x354302af",
                    "b": "0x6a09e667",
                    "c": "0xbb67ae85",
                    "d": "0x3c6ef372",
                    "e": "0xd2025d04",
                    "f": "0x510e527f",
                    "g": "0x9b05688c",
                    "h": "0x1f83d9ab",
                    "t1": "0x2cb267ca",
                    "t2": "0x08909ae5"
                },
                "2nd loop": {
                    "a": "0x22a50a8e",
                    "b": "0x354302af",
                    "c": "0x6a09e667",
                    "d": "0xbb67ae85",
                    "e": "0x4fac80f3",
                    "f": "0xd2025d04",
                    "g": "0x510e527f",
                    "h": "0x9b05688c",
                    "t1": "0x133d8d81",
                    "t2": "0x0f677d0d"
                },
                "3rd loop": {
                    "a": "0x5e04dd86",
                    "b": "0x22a50a8e",
                    "c": "0x354302af",
                    "d": "0x6a09e667",
                    "e": "0xae791a5b",
                    "f": "0x4fac80f3",
                    "g": "0xd2025d04",
                    "h": "0x510e527f",
                    "t1": "0xf3116bd6",
                    "t2": "0x6af371b0"
                },
                "4th loop": {
                    "a": "0xbd6ed14f",
                    "b": "0x5e04dd86",
                    "c": "0x22a50a8e",
                    "d": "0x354302af",
                    "e": "0x88adcee9",
                    "f": "0xae791a5b",
                    "g": "0x4fac80f3",
                    "h": "0xd2025d04",
                    "t1": "0x1ea3e882",
                    "t2": "0x9ecae8cd"
                },
                "5th loop": {
                    "a": "0x9a2d62b6",
                    "b": "0xbd6ed14f",
                    "c": "0x5e04dd86",
                    "d": "0x22a50a8e",
                    "e": "0xb2e82a07",
                    "f": "0x88adcee9",
                    "g": "0xae791a5b",
                    "h": "0x4fac80f3",
                    "t1": "0x7da52758",
                    "t2": "0x1c883b5e"
                },
                "6th loop": {
                    "a": "0x7e851b09",
                    "b": "0x9a2d62b6",
                    "c": "0xbd6ed14f",
                    "d": "0x5e04dd86",
                    "e": "0xfc480063",
                    "f": "0xb2e82a07",
                    "g": "0x88adcee9",
                    "h": "0xae791a5b",
                    "t1": "0xd9a2f5d5",
                    "t2": "0xa4e22534"
                },
                "7th loop": {
                    "a": "0x506238ee",
                    "b": "0x7e851b09",
                    "c": "0x9a2d62b6",
                    "d": "0xbd6ed14f",
                    "e": "0x5cb32c55",
                    "f": "0xfc480063",
                    "g": "0xb2e82a07",
                    "h": "0x88adcee9",
                    "t1": "0xfeae4ecf",
                    "t2": "0x51b3ea1f"
                },
                "8th loop": {
                    "a": "0x6344f0be",
                    "b": "0x506238ee",
                    "c": "0x7e851b09",
                    "d": "0x9a2d62b6",
                    "e": "0xeb04d2f4",
                    "f": "0x5cb32c55",
                    "g": "0xfc480063",
                    "h": "0xb2e82a07",
                    "t1": "0x2d9601a5",
                    "t2": "0x35aeef19"
                },
                "9th loop": {
                    "a": "0xf7b4f6cd",
                    "b": "0x6344f0be",
                    "c": "0x506238ee",
                    "d": "0x7e851b09",
                    "e": "0x10bd4150",
                    "f": "0xeb04d2f4",
                    "g": "0x5cb32c55",
                    "h": "0xfc480063",
                    "t1": "0x768fde9a",
                    "t2": "0x81251833"
                },
                "10th loop": {
                    "a": "0x1b70bb16",
                    "b": "0xf7b4f6cd",
                    "c": "0x6344f0be",
                    "d": "0x506238ee",
                    "e": "0x0e372d67",
                    "f": "0x10bd4150",
                    "g": "0xeb04d2f4",
                    "h": "0x5cb32c55",
                    "t1": "0x8fb2125e",
                    "t2": "0x8bbea8b8"
                },
                "11th loop": {
                    "a": "0x9d5fcf85",
                    "b": "0x1b70bb16",
                    "c": "0xf7b4f6cd",
                    "d": "0x6344f0be",
                    "e": "0xddcc68a8",
                    "f": "0x0e372d67",
                    "g": "0x10bd4150",
                    "h": "0xeb04d2f4",
                    "t1": "0x8d6a2fba",
                    "t2": "0x0ff59fcb"
                },
                "12th loop": {
                    "a": "0xa0596557",
                    "b": "0x9d5fcf85",
                    "c": "0x1b70bb16",
                    "d": "0xf7b4f6cd",
                    "e": "0xffe44726",
                    "f": "0xddcc68a8",
                    "g": "0x0e372d67",
                    "h": "0x10bd4150",
                    "t1": "0x9c9f5668",
                    "t2": "0x03ba0eef"
                },
                "13th loop": {
                    "a": "0x2eeefa46",
                    "b": "0xa0596557",
                    "c": "0x9d5fcf85",
                    "d": "0x1b70bb16",
                    "e": "0xe60bfcdd",
                    "f": "0xffe44726",
                    "g": "0xddcc68a8",
                    "h": "0x0e372d67",
                    "t1": "0xee570610",
                    "t2": "0x4097f436"
                },
                "14th loop": {
                    "a": "0x077864ac",
                    "b": "0x2eeefa46",
                    "c": "0xa0596557",
                    "d": "0x9d5fcf85",
                    "e": "0x94255f1e",
                    "f": "0xe60bfcdd",
                    "g": "0xffe44726",
                    "h": "0xddcc68a8",
                    "t1": "0x78b4a408",
                    "t2": "0x8ec3c0a4"
                },
                "15th loop": {
                    "a": "0xe03c6163",
                    "b": "0x077864ac",
                    "c": "0x2eeefa46",
                    "d": "0xa0596557",
                    "e": "0x91f739ad",
                    "f": "0x94255f1e",
                    "g": "0xe60bfcdd",
                    "h": "0xffe44726",
                    "t1": "0xf4976a28",
                    "t2": "0xeba4f73b"
                },
                "16th loop": {
                    "a": "0x59294260",
                    "b": "0xe03c6163",
                    "c": "0x077864ac",
                    "d": "0x2eeefa46",
                    "e": "0xd070b116",
                    "f": "0x91f739ad",
                    "g": "0x94255f1e",
                    "h": "0xe60bfcdd",
                    "t1": "0x30174bbf",
                    "t2": "0x2911f6a1"
                },
                "17th loop": {
                    "a": "0x00900871",
                    "b": "0x59294260",
                    "c": "0xe03c6163",
                    "d": "0x077864ac",
                    "e": "0x4e0589a1",
                    "f": "0xd070b116",
                    "g": "0x91f739ad",
                    "h": "0x94255f1e",
                    "t1": "0x1f168f5b",
                    "t2": "0xe1797916"
                },
                "18th loop": {
                    "a": "0x26ce3307",
                    "b": "0x00900871",
                    "c": "0x59294260",
                    "d": "0xe03c6163",
                    "e": "0xaa8094b4",
                    "f": "0x4e0589a1",
                    "g": "0xd070b116",
                    "h": "0x91f739ad",
                    "t1": "0xa3083008",
                    "t2": "0x83c602ff"
                },
                "19th loop": {
                    "a": "0x75467c42",
                    "b": "0x26ce3307",
                    "c": "0x00900871",
                    "d": "0x59294260",
                    "e": "0xebb43519",
                    "f": "0xaa8094b4",
                    "g": "0x4e0589a1",
                    "h": "0xd070b116",
                    "t1": "0x0b77d3b6",
                    "t2": "0x69cea88c"
                },
                "20th loop": {
                    "a": "0xe4868c7b",
                    "b": "0x75467c42",
                    "c": "0x26ce3307",
                    "d": "0x00900871",
                    "e": "0xb23659a2",
                    "f": "0xebb43519",
                    "g": "0xaa8094b4",
                    "h": "0x4e0589a1",
                    "t1": "0x590d1742",
                    "t2": "0x8b797539"
                },
                "21th loop": {
                    "a": "0x3f8dca66",
                    "b": "0xe4868c7b",
                    "c": "0x75467c42",
                    "d": "0x26ce3307",
                    "e": "0x5a882ddc",
                    "f": "0xb23659a2",
                    "g": "0xebb43519",
                    "h": "0xaa8094b4",
                    "t1": "0x59f8256b",
                    "t2": "0xe595a4fb"
                },
                "22th loop": {
                    "a": "0xc5ba599c",
                    "b": "0x3f8dca66",
                    "c": "0xe4868c7b",
                    "d": "0x75467c42",
                    "e": "0x8b06aa38",
                    "f": "0x5a882ddc",
                    "g": "0xb23659a2",
                    "h": "0xebb43519",
                    "t1": "0x64387731",
                    "t2": "0x6181e26b"
                },
                "23th loop": {
                    "a": "0x5fdbf49f",
                    "b": "0xc5ba599c",
                    "c": "0x3f8dca66",
                    "d": "0xe4868c7b",
                    "e": "0xdaa4dfc0",
                    "f": "0x8b06aa38",
                    "g": "0x5a882ddc",
                    "h": "0xb23659a2",
                    "t1": "0x655e637e",
                    "t2": "0xfa7d9121"
                },
                "24th loop": {
                    "a": "0x0404a527",
                    "b": "0x5fdbf49f",
                    "c": "0xc5ba599c",
                    "d": "0x3f8dca66",
                    "e": "0x6c10da7d",
                    "f": "0xdaa4dfc0",
                    "g": "0x8b06aa38",
                    "h": "0x5a882ddc",
                    "t1": "0x878a4e02",
                    "t2": "0x7c7a5725"
                },
                "25th loop": {
                    "a": "0x10c6080a",
                    "b": "0x0404a527",
                    "c": "0x5fdbf49f",
                    "d": "0xc5ba599c",
                    "e": "0x100b4755",
                    "f": "0x6c10da7d",
                    "g": "0xdaa4dfc0",
                    "h": "0x8b06aa38",
                    "t1": "0xd07d7cef",
                    "t2": "0x40488b1b"
                },
                "26th loop": {
                    "a": "0xf4c67097",
                    "b": "0x10c6080a",
                    "c": "0x0404a527",
                    "d": "0x5fdbf49f",
                    "e": "0xc978f9b3",
                    "f": "0x100b4755",
                    "g": "0x6c10da7d",
                    "h": "0xdaa4dfc0",
                    "t1": "0x03bea017",
                    "t2": "0xf107d080"
                },
                "27th loop": {
                    "a": "0x6218f6af",
                    "b": "0xf4c67097",
                    "c": "0x10c6080a",
                    "d": "0x0404a527",
                    "e": "0x4ce26582",
                    "f": "0xc978f9b3",
                    "g": "0x100b4755",
                    "h": "0x6c10da7d",
                    "t1": "0xed0670e3",
                    "t2": "0x751285cc"
                },
                "28th loop": {
                    "a": "0x7823abcc",
                    "b": "0x6218f6af",
                    "c": "0xf4c67097",
                    "d": "0x10c6080a",
                    "e": "0xfd3a4f80",
                    "f": "0x4ce26582",
                    "g": "0xc978f9b3",
                    "h": "0x100b4755",
                    "t1": "0xf935aa59",
                    "t2": "0x7eee0173"
                },
                "29th loop": {
                    "a": "0xc84c168d",
                    "b": "0x7823abcc",
                    "c": "0x6218f6af",
                    "d": "0xf4c67097",
                    "e": "0x9a4b11fa",
                    "f": "0xfd3a4f80",
                    "g": "0x4ce26582",
                    "h": "0xc978f9b3",
                    "t1": "0x898509f0",
                    "t2": "0x3ec70c9d"
                },
                "30th loop": {
                    "a": "0x30709a72",
                    "b": "0xc84c168d",
                    "c": "0x7823abcc",
                    "d": "0x6218f6af",
                    "e": "0xc706e39a",
                    "f": "0x9a4b11fa",
                    "g": "0xfd3a4f80",
                    "h": "0x4ce26582",
                    "t1": "0xd2407303",
                    "t2": "0x5e30276f"
                },
                "31th loop": {
                    "a": "0x49e6ef1a",
                    "b": "0x30709a72",
                    "c": "0xc84c168d",
                    "d": "0x7823abcc",
                    "e": "0x95badd24",
                    "f": "0xc706e39a",
                    "g": "0x9a4b11fa",
                    "h": "0xfd3a4f80",
                    "t1": "0x33a1e675",
                    "t2": "0x164508a5"
                },
                "32th loop": {
                    "a": "0x47a2b826",
                    "b": "0x49e6ef1a",
                    "c": "0x30709a72",
                    "d": "0xc84c168d",
                    "e": "0x064a2802",
                    "f": "0x95badd24",
                    "g": "0xc706e39a",
                    "h": "0x9a4b11fa",
                    "t1": "0x8e267c36",
                    "t2": "0xb97c3bf0"
                },
                "33th loop": {
                    "a": "0x67d857e2",
                    "b": "0x47a2b826",
                    "c": "0x49e6ef1a",
                    "d": "0x30709a72",
                    "e": "0x1407aa3b",
                    "f": "0x064a2802",
                    "g": "0x95badd24",
                    "h": "0xc706e39a",
                    "t1": "0x4bbb93ae",
                    "t2": "0x1c1cc434"
                },
                "34th loop": {
                    "a": "0x4bcc9a8d",
                    "b": "0x67d857e2",
                    "c": "0x47a2b826",
                    "d": "0x49e6ef1a",
                    "e": "0xec9f9338",
                    "f": "0x1407aa3b",
                    "g": "0x064a2802",
                    "h": "0x95badd24",
                    "t1": "0xbc2ef8c6",
                    "t2": "0x8f9da1c7"
                },
                "35th loop": {
                    "a": "0xa40cdbaf",
                    "b": "0x4bcc9a8d",
                    "c": "0x67d857e2",
                    "d": "0x47a2b826",
                    "e": "0xf137e23b",
                    "f": "0xec9f9338",
                    "g": "0x1407aa3b",
                    "h": "0x064a2802",
                    "t1": "0xa750f321",
                    "t2": "0xfcbbe88e"
                },
                "36th loop": {
                    "a": "0xaafd7432",
                    "b": "0xa40cdbaf",
                    "c": "0x4bcc9a8d",
                    "d": "0x67d857e2",
                    "e": "0x83c2a88c",
                    "f": "0xf137e23b",
                    "g": "0xec9f9338",
                    "h": "0x1407aa3b",
                    "t1": "0x3c1ff066",
                    "t2": "0x6edd83cc"
                },
                "37th loop": {
                    "a": "0x05bad06e",
                    "b": "0xaafd7432",
                    "c": "0xa40cdbaf",
                    "d": "0x4bcc9a8d",
                    "e": "0xc3cb8d55",
                    "f": "0x83c2a88c",
                    "g": "0xf137e23b",
                    "h": "0xec9f9338",
                    "t1": "0x5bf33573",
                    "t2": "0xa9c79afb"
                },
                "38th loop": {
                    "a": "0x36eac389",
                    "b": "0x05bad06e",
                    "c": "0xaafd7432",
                    "d": "0xa40cdbaf",
                    "e": "0xf49b6c0d",
                    "f": "0xc3cb8d55",
                    "g": "0x83c2a88c",
                    "h": "0xf137e23b",
                    "t1": "0xa8ced180",
                    "t2": "0x8e1bf209"
                },
                "39th loop": {
                    "a": "0x062384e7",
                    "b": "0x36eac389",
                    "c": "0x05bad06e",
                    "d": "0xaafd7432",
                    "e": "0x88386cfd",
                    "f": "0xf49b6c0d",
                    "g": "0xc3cb8d55",
                    "h": "0x83c2a88c",
                    "t1": "0xe42b914e",
                    "t2": "0x21f7f399"
                },
                "40th loop": {
                    "a": "0xe46fb76c",
                    "b": "0x062384e7",
                    "c": "0x36eac389",
                    "d": "0x05bad06e",
                    "e": "0x201f1e72",
                    "f": "0x88386cfd",
                    "g": "0xf49b6c0d",
                    "h": "0xc3cb8d55",
                    "t1": "0x7521aa40",
                    "t2": "0x6f4e0d2c"
                },
                "41th loop": {
                    "a": "0xd76c85e9",
                    "b": "0xe46fb76c",
                    "c": "0x062384e7",
                    "d": "0x36eac389",
                    "e": "0x7a1a5133",
                    "f": "0x201f1e72",
                    "g": "0x88386cfd",
                    "h": "0xf49b6c0d",
                    "t1": "0x745f80c5",
                    "t2": "0x630d0524"
                },
                "42th loop": {
                    "a": "0xf701fc92",
                    "b": "0xd76c85e9",
                    "c": "0xe46fb76c",
                    "d": "0x062384e7",
                    "e": "0x7efafceb",
                    "f": "0x7a1a5133",
                    "g": "0x201f1e72",
                    "h": "0x88386cfd",
                    "t1": "0x48103962",
                    "t2": "0xaef1c330"
                },
                "43th loop": {
                    "a": "0x2351d593",
                    "b": "0xf701fc92",
                    "c": "0xd76c85e9",
                    "d": "0xe46fb76c",
                    "e": "0xd362179b",
                    "f": "0x7efafceb",
                    "g": "0x7a1a5133",
                    "h": "0x201f1e72",
                    "t1": "0xcd3e92b4",
                    "t2": "0x561342df"
                },
                "44th loop": {
                    "a": "0x0b558974",
                    "b": "0x2351d593",
                    "c": "0xf701fc92",
                    "d": "0xd76c85e9",
                    "e": "0xd56847e6",
                    "f": "0xd362179b",
                    "g": "0x7efafceb",
                    "h": "0x7a1a5133",
                    "t1": "0xf0f8907a",
                    "t2": "0x1a5cf8fa"
                },
                "45th loop": {
                    "a": "0x67000597",
                    "b": "0x0b558974",
                    "c": "0x2351d593",
                    "d": "0xf701fc92",
                    "e": "0xfbc9c512",
                    "f": "0xd56847e6",
                    "g": "0xd362179b",
                    "h": "0x7efafceb",
                    "t1": "0x245d3f29",
                    "t2": "0x42a2c66e"
                },
                "46th loop": {
                    "a": "0xb1502b42",
                    "b": "0x67000597",
                    "c": "0x0b558974",
                    "d": "0x2351d593",
                    "e": "0x8f933d44",
                    "f": "0xfbc9c512",
                    "g": "0xd56847e6",
                    "h": "0xd362179b",
                    "t1": "0x989140b2",
                    "t2": "0x18beea90"
                },
                "47th loop": {
                    "a": "0x0965f7ac",
                    "b": "0xb1502b42",
                    "c": "0x67000597",
                    "d": "0x0b558974",
                    "e": "0x527b3955",
                    "f": "0x8f933d44",
                    "g": "0xfbc9c512",
                    "h": "0xd56847e6",
                    "t1": "0x2f2963c2",
                    "t2": "0xda3c93ea"
                },
                "48th loop": {
                    "a": "0x99ddfbc5",
                    "b": "0x0965f7ac",
                    "c": "0xb1502b42",
                    "d": "0x67000597",
                    "e": "0x5b0bd6d2",
                    "f": "0x527b3955",
                    "g": "0x8f933d44",
                    "h": "0xfbc9c512",
                    "t1": "0x4fb64d5e",
                    "t2": "0x4a27ae67"
                },
                "49th loop": {
                    "a": "0x37fd005d",
                    "b": "0x99ddfbc5",
                    "c": "0x0965f7ac",
                    "d": "0xb1502b42",
                    "e": "0x35f263b7",
                    "f": "0x5b0bd6d2",
                    "g": "0x527b3955",
                    "h": "0x8f933d44",
                    "t1": "0xcef25e20",
                    "t2": "0x690aa23d"
                },
                "50th loop": {
                    "a": "0xa3ddcac6",
                    "b": "0x37fd005d",
                    "c": "0x99ddfbc5",
                    "d": "0x0965f7ac",
                    "e": "0x8018771b",
                    "f": "0x35f263b7",
                    "g": "0x5b0bd6d2",
                    "h": "0x527b3955",
                    "t1": "0xcec84bd9",
                    "t2": "0xd5157eed"
                },
                "51th loop": {
                    "a": "0x2f3bbb35",
                    "b": "0xa3ddcac6",
                    "c": "0x37fd005d",
                    "d": "0x99ddfbc5",
                    "e": "0xfada714c",
                    "f": "0x8018771b",
                    "g": "0x35f263b7",
                    "h": "0x5b0bd6d2",
                    "t1": "0xf17479a0",
                    "t2": "0x3dc74195"
                },
                "52th loop": {
                    "a": "0x659f10f7",
                    "b": "0x2f3bbb35",
                    "c": "0xa3ddcac6",
                    "d": "0x37fd005d",
                    "e": "0x5af43ebb",
                    "f": "0xfada714c",
                    "g": "0x8018771b",
                    "h": "0x35f263b7",
                    "t1": "0xc11642f6",
                    "t2": "0xa488ce01"
                },
                "53th loop": {
                    "a": "0x3a9c3eff",
                    "b": "0x659f10f7",
                    "c": "0x2f3bbb35",
                    "d": "0xa3ddcac6",
                    "e": "0x285a6f12",
                    "f": "0x5af43ebb",
                    "g": "0xfada714c",
                    "h": "0x8018771b",
                    "t1": "0xf05d6eb5",
                    "t2": "0x4a3ed04a"
                },
                "54th loop": {
                    "a": "0x0176ca98",
                    "b": "0x3a9c3eff",
                    "c": "0x659f10f7",
                    "d": "0x2f3bbb35",
                    "e": "0x2c1032b3",
                    "f": "0x285a6f12",
                    "g": "0x5af43ebb",
                    "h": "0xfada714c",
                    "t1": "0x883267ed",
                    "t2": "0x794462ab"
                },
                "55th loop": {
                    "a": "0xd584f572",
                    "b": "0x0176ca98",
                    "c": "0x3a9c3eff",
                    "d": "0x659f10f7",
                    "e": "0x536abc93",
                    "f": "0x2c1032b3",
                    "g": "0x285a6f12",
                    "h": "0x5af43ebb",
                    "t1": "0x242f015e",
                    "t2": "0xb155f414"
                },
                "56th loop": {
                    "a": "0x13fd5938",
                    "b": "0xd584f572",
                    "c": "0x0176ca98",
                    "d": "0x3a9c3eff",
                    "e": "0x5ae51108",
                    "f": "0x536abc93",
                    "g": "0x2c1032b3",
                    "h": "0x285a6f12",
                    "t1": "0xf5460011",
                    "t2": "0x1eb75927"
                },
                "57th loop": {
                    "a": "0xc846e4c1",
                    "b": "0x13fd5938",
                    "c": "0xd584f572",
                    "d": "0x0176ca98",
                    "e": "0xb893209d",
                    "f": "0x5ae51108",
                    "g": "0x536abc93",
                    "h": "0x2c1032b3",
                    "t1": "0x7df6e19e",
                    "t2": "0x4a500323"
                },
                "58th loop": {
                    "a": "0xf298071d",
                    "b": "0xc846e4c1",
                    "c": "0x13fd5938",
                    "d": "0xd584f572",
                    "e": "0xd2bce01f",
                    "f": "0xb893209d",
                    "g": "0x5ae51108",
                    "h": "0x536abc93",
                    "t1": "0xd1461587",
                    "t2": "0x2151f196"
                },
                "59th loop": {
                    "a": "0x5f2b50a4",
                    "b": "0xf298071d",
                    "c": "0xc846e4c1",
                    "d": "0x13fd5938",
                    "e": "0x3d7e1e30",
                    "f": "0xd2bce01f",
                    "g": "0xb893209d",
                    "h": "0x5ae51108",
                    "t1": "0x67f928be",
                    "t2": "0xf73227e6"
                },
                "60th loop": {
                    "a": "0xa28a6729",
                    "b": "0x5f2b50a4",
                    "c": "0xf298071d",
                    "d": "0xc846e4c1",
                    "e": "0x9cd2bfcd",
                    "f": "0x3d7e1e30",
                    "g": "0xd2bce01f",
                    "h": "0xb893209d",
                    "t1": "0x88d56695",
                    "t2": "0x19b50094"
                },
                "61th loop": {
                    "a": "0x246340d7",
                    "b": "0xa28a6729",
                    "c": "0x5f2b50a4",
                    "d": "0xf298071d",
                    "e": "0x81acb358",
                    "f": "0x9cd2bfcd",
                    "g": "0x3d7e1e30",
                    "h": "0xd2bce01f",
                    "t1": "0xb965ce97",
                    "t2": "0x6afd7240"
                },
                "62th loop": {
                    "a": "0x47b8ba4e",
                    "b": "0x246340d7",
                    "c": "0xa28a6729",
                    "d": "0x5f2b50a4",
                    "e": "0xd182d108",
                    "f": "0x81acb358",
                    "g": "0x9cd2bfcd",
                    "h": "0x3d7e1e30",
                    "t1": "0xdeeac9eb",
                    "t2": "0x68cdf063"
                },
                "63th loop": {
                    "a": "0xd3eccb2e",
                    "b": "0x47b8ba4e",
                    "c": "0x246340d7",
                    "d": "0xa28a6729",
                    "e": "0x6af88f3b",
                    "f": "0xd182d108",
                    "g": "0x81acb358",
                    "h": "0x9cd2bfcd",
                    "t1": "0x0bcd3e97",
                    "t2": "0xc81f8c97"
                },
                "64th loop": {
                    "a": "0xa6ac91ef",
                    "b": "0xd3eccb2e",
                    "c": "0x47b8ba4e",
                    "d": "0x246340d7",
                    "e": "0xa2ad17e8",
                    "f": "0x6af88f3b",
                    "g": "0xd182d108",
                    "h": "0x81acb358",
                    "t1": "0x0022b0bf",
                    "t2": "0xa689e130"
                }
            },
            "Finalize the hash value(Step4)": {
                "a": "0x10b67856",
                "b": "0x8f5479b3",
                "c": "0x8427adc0",
                "d": "0xc9b33611",
                "e": "0xf3bb6a67",
                "f": "0x05fdf7c7",
                "g": "0xf106aab3",
                "h": "0xdd8d8071"
            }
        }
    }
}